oneNeuron/__init__.py
oneNeuron/perceptron.py
Testing_pypi_nik_vaibhav18-0.0.2.dist-info/LICENSE
Testing_pypi_nik_vaibhav18-0.0.2.dist-info/METADATA
Testing_pypi_nik_vaibhav18-0.0.2.dist-info/WHEEL
Testing_pypi_nik_vaibhav18-0.0.2.dist-info/top_level.txt
Testing_pypi_nik_vaibhav18-0.0.2.dist-info/RECORD
