Metadata-Version: 2.1
Name: Testing-pypi-nik-vaibhav18
Version: 0.0.2
Summary: updated readme
Home-page: https://github.com/nik-vaibhav18/Testing_pypi
Author: nik-vaibhav18
Author-email: nik.vaibhav18@gmail.com
License: UNKNOWN
Project-URL: Bug Tracker, https://github.com/nik-vaibhav18/Testing_pypi/issues
Platform: UNKNOWN
Classifier: Programming Language :: Python :: 3
Classifier: License :: OSI Approved :: MIT License
Classifier: Operating System :: OS Independent
Requires-Python: >=3.7
License-File: LICENSE
Requires-Dist: numpy
Requires-Dist: tqdm
